setup.py
mysql_replication_watcher.egg-info/PKG-INFO
mysql_replication_watcher.egg-info/SOURCES.txt
mysql_replication_watcher.egg-info/dependency_links.txt
mysql_replication_watcher.egg-info/requires.txt
mysql_replication_watcher.egg-info/top_level.txt
pymysqlreplication/__init__.py
pymysqlreplication/_compat.py
pymysqlreplication/binlogstream.py
pymysqlreplication/bitmap.py
pymysqlreplication/column.py
pymysqlreplication/event.py
pymysqlreplication/exceptions.py
pymysqlreplication/gtid.py
pymysqlreplication/packet.py
pymysqlreplication/row_event.py
pymysqlreplication/table.py
pymysqlreplication/watcher.py
pymysqlreplication/constants/BINLOG.py
pymysqlreplication/constants/FIELD_TYPE.py
pymysqlreplication/constants/__init__.py
pymysqlreplication/tests/__init__.py
pymysqlreplication/tests/base.py
pymysqlreplication/tests/benchmark.py
pymysqlreplication/tests/binlogfilereader.py
pymysqlreplication/tests/test_abnormal.py
pymysqlreplication/tests/test_basic.py
pymysqlreplication/tests/test_data_objects.py
pymysqlreplication/tests/test_data_type.py