Metadata-Version: 2.1
Name: mysql-replication-watcher
Version: 0.23
Summary: Pure Python Implementation of MySQL replication protocol build on top of PyMYSQL.
Home-page: https://github.com/laik/python-mysql-replication
Author: Julien Duponchelle
Author-email: yoshiakiley@gmail.com
License: Apache 2
Platform: UNKNOWN
Provides-Extra: test
